pybaycor/__init__.py
pybaycor/pybaycor.py
pybaycor-0.2.1.dist-info/LICENSE
pybaycor-0.2.1.dist-info/METADATA
pybaycor-0.2.1.dist-info/WHEEL
pybaycor-0.2.1.dist-info/top_level.txt
pybaycor-0.2.1.dist-info/RECORD
