Metadata-Version: 2.1
Name: pybaycor
Version: 0.2.1
Summary: A package for Bayesian inference of correlations
Home-page: https://github.com/pscicluna/pybaycor
Author: Peter Scicluna
Author-email: peter.scicluna@eso.org
License: MIT
Project-URL: Bug Tracker, https://github.com/pscicluna/pybaycor/issues
Platform: UNKNOWN
Classifier: Development Status :: 3 - Alpha
Classifier: Intended Audience :: Science/Research
Classifier: License :: OSI Approved :: MIT License
Classifier: Operating System :: POSIX :: Linux
Classifier: Programming Language :: Python :: 3
Requires-Python: >=3.7
Requires-Dist: numpy
Requires-Dist: matplotlib
Requires-Dist: seaborn
Requires-Dist: xarray
Requires-Dist: pymc3 (==3.10.0)
Requires-Dist: arviz (==0.11.0)
